opengraph/__init__.py
opengraph/__version__.py
opengraph/opengraph.py
python_opengraph_jaywink-0.2.1.dist-info/LICENSE
python_opengraph_jaywink-0.2.1.dist-info/METADATA
python_opengraph_jaywink-0.2.1.dist-info/WHEEL
python_opengraph_jaywink-0.2.1.dist-info/top_level.txt
python_opengraph_jaywink-0.2.1.dist-info/RECORD
