Metadata-Version: 2.1
Name: python-opengraph-jaywink
Version: 0.2.1
Summary: Python module to parse Open Graph metadata on web pages
Home-page: https://github.com/jaywink/python-opengraph
Author: Jason Robinson
Author-email: mail@jasonrobinson.me
License: MIT
Keywords: opengraph
Platform: UNKNOWN
Classifier: Development Status :: 3 - Alpha
Classifier: Intended Audience :: Developers
Classifier: License :: OSI Approved :: MIT License
Classifier: Programming Language :: Python :: 3
Classifier: Programming Language :: Python :: 3.4
Classifier: Programming Language :: Python :: 3.5
Classifier: Programming Language :: Python :: 3.6
License-File: LICENSE
Requires-Dist: beautifulsoup4 (>=4.3)
Requires-Dist: requests (>=2.7)
